product2vec/__init__.py
product2vec/base.py
product2vec/data.py
product2vec/model.py
product2vec/model_tools.py
product2vec-0.1.0.dist-info/LICENSE
product2vec-0.1.0.dist-info/METADATA
product2vec-0.1.0.dist-info/WHEEL
product2vec-0.1.0.dist-info/top_level.txt
product2vec-0.1.0.dist-info/RECORD
