Metadata-Version: 2.1
Name: product2vec
Version: 0.1.0
Summary: Product2Vec model for finding complementary and fungible products
Author-email: Theo Vall <fedorvall.ds@gmail.com>
License: MIT License
Project-URL: Homepage, https://github.com/TheoVall-DS/product2vec
Keywords: Word2Vec,complementary goods,fungible goods
Classifier: Development Status :: 4 - Beta
Classifier: Intended Audience :: Science/Research
Classifier: Intended Audience :: Developers
Classifier: License :: OSI Approved :: MIT License
Classifier: Programming Language :: Python
Classifier: Programming Language :: Python :: 3
Classifier: Programming Language :: Python :: 3.8
Classifier: Programming Language :: Python :: 3.9
Classifier: Programming Language :: Python :: 3.10
Classifier: Programming Language :: Python :: 3.11
Classifier: Topic :: Software Development :: Libraries
Classifier: Topic :: Scientific/Engineering
Classifier: Operating System :: OS Independent
Requires-Python: >=3.8
License-File: LICENSE
Requires-Dist: gensim >=4.3.1
Requires-Dist: joblib >=1.2.0
Requires-Dist: numpy >=1.24.3
Requires-Dist: scipy >=1.10.1
Provides-Extra: dev
Requires-Dist: black >=22.6.0 ; extra == 'dev'
Requires-Dist: isort >=5.9.3 ; extra == 'dev'
Requires-Dist: pylint >=2.14.5 ; extra == 'dev'
Requires-Dist: pytest >=7.1.3 ; extra == 'dev'
Requires-Dist: pytest-cov >=4.0.0 ; extra == 'dev'
